aphrodite/_C.abi3.so
aphrodite/__init__.py
aphrodite/_core_C.abi3.so
aphrodite/_core_ext.py
aphrodite/_custom_ops.py
aphrodite/_ipex_ops.py
aphrodite/_moe_C.abi3.so
aphrodite/commit_id.py
aphrodite/connections.py
aphrodite/constants.py
aphrodite/py.typed
aphrodite/scalar_type.py
aphrodite/version.py
aphrodite/adapter_commons/__init__.py
aphrodite/adapter_commons/layers.py
aphrodite/adapter_commons/models.py
aphrodite/adapter_commons/request.py
aphrodite/adapter_commons/utils.py
aphrodite/adapter_commons/worker_manager.py
aphrodite/assets/__init__.py
aphrodite/assets/audio.py
aphrodite/assets/base.py
aphrodite/assets/image.py
aphrodite/attention/__init__.py
aphrodite/attention/layer.py
aphrodite/attention/selector.py
aphrodite/attention/backends/__init__.py
aphrodite/attention/backends/abstract.py
aphrodite/attention/backends/blocksparse_attn.py
aphrodite/attention/backends/flash_attn.py
aphrodite/attention/backends/flashinfer.py
aphrodite/attention/backends/ipex_attn.py
aphrodite/attention/backends/openvino.py
aphrodite/attention/backends/pallas.py
aphrodite/attention/backends/placeholder_attn.py
aphrodite/attention/backends/rocm_flash_attn.py
aphrodite/attention/backends/torch_sdpa.py
aphrodite/attention/backends/utils.py
aphrodite/attention/backends/xformers.py
aphrodite/attention/ops/__init__.py
aphrodite/attention/ops/ipex_attn.py
aphrodite/attention/ops/paged_attn.py
aphrodite/attention/ops/prefix_prefill.py
aphrodite/attention/ops/triton_flash_attn.py
aphrodite/attention/ops/blocksparse_attention/__init__.py
aphrodite/attention/ops/blocksparse_attention/blocksparse_attention_kernel.py
aphrodite/attention/ops/blocksparse_attention/interface.py
aphrodite/attention/ops/blocksparse_attention/utils.py
aphrodite/common/__init__.py
aphrodite/common/block.py
aphrodite/common/config.py
aphrodite/common/connections.py
aphrodite/common/envs.py
aphrodite/common/grammar.py
aphrodite/common/logger.py
aphrodite/common/logits_processor.py
aphrodite/common/outputs.py
aphrodite_engine-0.6.5.dist-info/LICENSE
aphrodite_engine-0.6.5.dist-info/METADATA
aphrodite_engine-0.6.5.dist-info/WHEEL
aphrodite_engine-0.6.5.dist-info/entry_points.txt
aphrodite_engine-0.6.5.dist-info/top_level.txt
aphrodite_engine-0.6.5.dist-info/RECORD
