Metadata-Version: 2.1
Name: aphrodite-engine
Version: 0.6.5
Summary: The inference engine for PygmalionAI models
Home-page: https://github.com/PygmalionAI/aphrodite-engine
Author: PygmalionAI
License: AGPL 3.0
Project-URL: Homepage, https://pygmalion.chat
Project-URL: Documentation, https://docs.pygmalion.chat
Project-URL: GitHub, https://github.com/PygmalionAI
Project-URL: Huggingface, https://huggingface.co/PygmalionAI
Classifier: Programming Language :: Python :: 3
Classifier: License :: OSI Approved :: GNU Affero General Public License v3 or later (AGPLv3+)
Classifier: Topic :: Scientific/Engineering :: Artificial Intelligence
Requires-Python: >=3.8
License-File: LICENSE
Requires-Dist: psutil
Requires-Dist: sentencepiece
Requires-Dist: numpy<2.0.0
Requires-Dist: requests
Requires-Dist: tqdm
Requires-Dist: py-cpuinfo
Requires-Dist: transformers==4.45.2
Requires-Dist: tokenizers>=0.19.1
Requires-Dist: fastapi
Requires-Dist: aiohttp
Requires-Dist: openai
Requires-Dist: uvicorn[standard]
Requires-Dist: pydantic>=2.0
Requires-Dist: pillow
Requires-Dist: prometheus_client>=0.18.0
Requires-Dist: prometheus-fastapi-instrumentator>=7.0.0
Requires-Dist: tiktoken>=0.6.0
Requires-Dist: lm-format-enforcer<0.11,>=0.10.9
Requires-Dist: outlines<0.1,>=0.0.43
Requires-Dist: typing_extensions>=4.10
Requires-Dist: filelock>=3.10.4
Requires-Dist: pyzmq
Requires-Dist: scipy
Requires-Dist: rich
Requires-Dist: loguru
Requires-Dist: hf_transfer
Requires-Dist: librosa
Requires-Dist: soundfile
Requires-Dist: gguf>=0.10.0
Requires-Dist: importlib_metadata
Requires-Dist: mistral_common>=1.5.0
Requires-Dist: protobuf
Requires-Dist: pandas
Requires-Dist: msgspec
Requires-Dist: python-multipart
Requires-Dist: nvidia-ml-py==12.555.43
Requires-Dist: torch==2.4.0; platform_system == "Linux"
Requires-Dist: torchvision==0.19; platform_system == "Linux"
Requires-Dist: xformers==0.0.27.post2; platform_system == "Linux" and platform_machine == "x86_64"
Requires-Dist: triton>=2.2.1; platform_system == "Linux"
Requires-Dist: aphrodite-flash-attn==2.6.1.post2; platform_system == "Linux" and platform_machine == "x86_64"
Requires-Dist: winloop; platform_system == "Windows"
Requires-Dist: tornado; platform_system == "Windows"
Provides-Extra: flash-attn
Requires-Dist: flash-attn==2.5.8; extra == "flash-attn"
Provides-Extra: tensorizer
Requires-Dist: tensorizer>=2.9.0; extra == "tensorizer"
Provides-Extra: ray
Requires-Dist: ray>=2.9; extra == "ray"
